pybmengine/__init__.py
pybmengine/data.py
pybmengine/server.py
pybmengine-0.0.1.dist-info/METADATA
pybmengine-0.0.1.dist-info/WHEEL
pybmengine-0.0.1.dist-info/top_level.txt
pybmengine-0.0.1.dist-info/RECORD
