Metadata-Version: 2.1
Name: pybmengine
Version: 0.0.1
Summary: BMEngine fastapi http gate
Author: a710128
Author-email: qbjooo@qq.com
License: UNKNOWN
Platform: UNKNOWN
Classifier: Programming Language :: Python :: 3
Classifier: License :: OSI Approved :: MIT License
Classifier: Programming Language :: C++
Requires-Python: >=3.6
Requires-Dist: fastapi
Requires-Dist: uvicorn[standard]
